MANIFEST.in
coco.py
reqs.txt
setup.py
coco.egg-info/PKG-INFO
coco.egg-info/SOURCES.txt
coco.egg-info/dependency_links.txt
coco.egg-info/entry_points.txt
coco.egg-info/not-zip-safe
coco.egg-info/requires.txt
coco.egg-info/top_level.txt