Metadata-Version: 1.0
Name: coco
Version: 0.1.2.2
Summary: battery health & more
Home-page: https://cwoebker.com/projects/coco
Author: Cecil Woebker
Author-email: cwoebker@gmail.com
License: UNKNOWN
Platform: UNKNOWN
Classifier: Development Status :: 5 - Production/Stable
Classifier: Intended Audience :: Developers
Classifier: Intended Audience :: System Administrators
Classifier: Natural Language :: English
Classifier: Topic :: Software Development
Classifier: License :: OSI Approved :: BSD License
Classifier: Programming Language :: Python
Classifier: Programming Language :: Python :: 2.6
Classifier: Programming Language :: Python :: 2.7
